FlexibleNetwork/Flexible_Network.py
FlexibleNetwork/Integrations.py
FlexibleNetwork/Terminal_Task.py
FlexibleNetwork/Vendors.py
FlexibleNetwork/__init__.py
FlexibleNetwork/cli.py
FlexibleNetwork/colors.py
FlexibleNetwork/inventory.py
FlexibleNetwork/read_cli_options.py
FlexibleNetwork/read_config.py
FlexibleNetwork/ssh.py
FlexibleNetwork/ssh_authentication.py
FlexibleNetwork/tinydb_db.py
FlexibleNetwork/yaml_parser.py
FlexibleNetwork/integrations/__init__.py
FlexibleNetwork/integrations/cyberark.py
FlexibleNetwork/integrations/rocket_chat.py
FlexibleNetwork/integrations/s3.py
FlexibleNetwork/integrations/vault-test.py
FlexibleNetwork/integrations/vault.py
FlexibleNetwork/vendors/__init__.py
FlexibleNetwork/vendors/cisco.py
FlexibleNetwork/vendors/huawei.py
FlexibleNetwork-0.3.1.dist-info/METADATA
FlexibleNetwork-0.3.1.dist-info/WHEEL
FlexibleNetwork-0.3.1.dist-info/top_level.txt
FlexibleNetwork-0.3.1.dist-info/RECORD
